<?xml version="1.0"?>
<resources>
    <set path = "resources/images/terrain/" />
    <atlas linearFilter = "false">
        <image file="plains/plains+0.png" />
        <image file="plains/plains+1.png" />
        <image file="plains/plains+2.png" />
        <image file="plains/plains+3.png" />
        <image file="plains/plains+4.png" />
        <image file="plains/plains+5.png" />
        <image file="plains/plains+6.png" />
        <image file="plains/plains+7.png" />
        <image file="plains/plains+8.png" />
        <image file="plains/plains+9.png" />
        <image file="plains/plains+10.png" />
        <image file="plains/plains+11.png" />
        <image file="plains/plains+12.png" />
        <image file="plains/plains+13.png" />
        <image file="plains/plains+14.png" />
        <image file="plains/plains+15.png" />
        <image file="plains/plains+16.png" />
        <image file="plains/plains+17.png" />
        <image file="plains/plains+18.png" />
        <image file="plains/plains+19.png" />
        <image file="plains/plains+20.png" />
        <image file="plains/plains+21.png" />
        <image file="plains/plains+destroyed.png" />
        <image file="plains/shadow_plains.png" />        
        <image file="plains/plains+plasma.png" />
        <image file="plains/plains+plasma+E.png" />
        <image file="plains/plains+plasma+E+S.png" />
        <image file="plains/plains+plasma+E+S+W.png" />
        <image file="plains/plains+plasma+E+W.png" />
        <image file="plains/plains+plasma+N.png" />
        <image file="plains/plains+plasma+N+E.png" />
        <image file="plains/plains+plasma+N+E+S.png" />
        <image file="plains/plains+plasma+N+E+S+W.png" />
        <image file="plains/plains+plasma+N+E+W.png" />
        <image file="plains/plains+plasma+N+S.png" />
        <image file="plains/plains+plasma+N+S+W.png" />
        <image file="plains/plains+plasma+N+W.png" />
        <image file="plains/plains+plasma+S.png" />
        <image file="plains/plains+plasma+S+W.png" />
        <image file="plains/plains+plasma+W.png" />
        <image file="plains/plains+W.png" />
        <image file="plains/plains+S.png" />
        <image file="plains/plains+E.png" />
        <image file="plains/plains+N.png" />
        
        <image file="sea/sea+mask.png" cols = "8" />
        <image file="sea/sea+N+mask.png" cols = "8" />
        <image file="sea/sea+E+mask.png" cols = "8" />
        <image file="sea/sea+S+mask.png" cols = "8" />
        <image file="sea/sea+W+mask.png" cols = "8" />
        <image file="sea/sea+E+SW+NW+mask.png" cols = "8" />
        <image file="sea/sea+E+SW+mask.png" cols = "8" />
        <image file="sea/sea+E+NW+mask.png" cols = "8" />
        <image file="sea/sea+N+SE+SW+mask.png" cols = "8" />
        <image file="sea/sea+N+SE+mask.png" cols = "8" />
        <image file="sea/sea+N+SW+mask.png" cols = "8" />
        <image file="sea/sea+W+NE+SE+mask.png" cols = "8" />
        <image file="sea/sea+W+NE+mask.png" cols = "8" />
        <image file="sea/sea+W+SE+mask.png" cols = "8" />
        <image file="sea/sea+S+NE+NW+mask.png" cols = "8" />
        <image file="sea/sea+S+NE+mask.png" cols = "8" />
        <image file="sea/sea+S+NW+mask.png" cols = "8" />
        <image file="sea/sea+N+E+mask.png" cols = "8" />
        <image file="sea/sea+E+S+mask.png" cols = "8" />
        <image file="sea/sea+E+W+mask.png" cols = "8" />
        <image file="sea/sea+N+S+mask.png" cols = "8" />
        <image file="sea/sea+N+W+mask.png" cols = "8" />
        <image file="sea/sea+S+W+mask.png" cols = "8" />
        <image file="sea/sea+N+W+SE+mask.png" cols = "8" />
        <image file="sea/sea+E+S+NW+mask.png" cols = "8" />
        <image file="sea/sea+S+W+NE+mask.png" cols = "8" />
        <image file="sea/sea+N+E+SW+mask.png" cols = "8" />
        <image file="sea/sea+E+S+W+mask.png" cols = "8" />
        <image file="sea/sea+N+E+S+mask.png" cols = "8" />
        <image file="sea/sea+N+E+W+mask.png" cols = "8" />
        <image file="sea/sea+N+S+W+mask.png" cols = "8" />
        <image file="sea/sea+N+E+S+W+mask.png" cols = "8" />
        <image file="sea/sea+NE+SE+SW+NW+mask.png" cols = "8" />
        <image file="sea/sea+NE+SW+NW+mask.png" cols = "8" />
        <image file="sea/sea+NE+SE+SW+mask.png" cols = "8" />
        <image file="sea/sea+SE+SW+NW+mask.png" cols = "8" />
        <image file="sea/sea+NE+SE+NW+mask.png" cols = "8" />
        <image file="sea/sea+NE+NW+mask.png" cols = "8" />
        <image file="sea/sea+NE+SE+mask.png" cols = "8" />
        <image file="sea/sea+NE+SW+mask.png" cols = "8" />
        <image file="sea/sea+SE+NW+mask.png" cols = "8" />
        <image file="sea/sea+SW+NW+mask.png" cols = "8" />
        <image file="sea/sea+SE+SW+mask.png" cols = "8" />
        <image file="sea/sea+NE+mask.png" cols = "8" />
        <image file="sea/sea+NW+mask.png" cols = "8" />
        <image file="sea/sea+SE+mask.png" cols = "8" />
        <image file="sea/sea+SW+mask.png" cols = "8" />
        <image file="sea/sea+NE+overlay+mask.png" cols = "8" />
        <image file="sea/sea+NW+overlay+mask.png" cols = "8" />
        <image file="sea/sea+SE+overlay+mask.png" cols = "8" />
        <image file="sea/sea+SW+overlay+mask.png" cols = "8" />
        <image file="sea/sea+E+W+bridge+mask.png" cols = "8" />
        <image file="sea/sea+W+bridge+mask.png" cols = "8" />
        <image file="sea/sea+E+bridge+mask.png" cols = "8" />
        <!-- sea overlay for other terrain types -->
        <image file="sea/sea+snow+E+mask.png" />
        <image file="sea/sea+snow+E+S+mask.png" />
        <image file="sea/sea+snow+E+S+W+mask.png" />
        <image file="sea/sea+snow+E+W+mask.png" />
        <image file="sea/sea+snow+N+mask.png" />
        <image file="sea/sea+snow+N+E+mask.png" />
        <image file="sea/sea+snow+N+E+S+mask.png" />
        <image file="sea/sea+snow+N+E+S+W+mask.png" />
        <image file="sea/sea+snow+N+E+W+mask.png" />
        <image file="sea/sea+snow+N+S+mask.png" />
        <image file="sea/sea+snow+N+S+W+mask.png" />
        <image file="sea/sea+snow+N+W+mask.png" />
        <image file="sea/sea+snow+S+mask.png" />
        <image file="sea/sea+snow+S+W+mask.png" />
        <image file="sea/sea+snow+W+mask.png" />
        <image file="sea/sea+desert+E+mask.png" />
        <image file="sea/sea+desert+E+S+mask.png" />
        <image file="sea/sea+desert+E+S+W+mask.png" />
        <image file="sea/sea+desert+E+W+mask.png" />
        <image file="sea/sea+desert+N+mask.png" />
        <image file="sea/sea+desert+N+E+mask.png" />
        <image file="sea/sea+desert+N+E+S+mask.png" />
        <image file="sea/sea+desert+N+E+S+W+mask.png" />
        <image file="sea/sea+desert+N+E+W+mask.png" />
        <image file="sea/sea+desert+N+S+mask.png" />
        <image file="sea/sea+desert+N+S+W+mask.png" />
        <image file="sea/sea+desert+N+W+mask.png" />
        <image file="sea/sea+desert+S+mask.png" />
        <image file="sea/sea+desert+S+W+mask.png" />
        <image file="sea/sea+desert+W+mask.png" />
        <image file="sea/sea+waste+E+mask.png" />
        <image file="sea/sea+waste+E+S+mask.png"  />
        <image file="sea/sea+waste+E+S+W+mask.png" />
        <image file="sea/sea+waste+E+W+mask.png" />
        <image file="sea/sea+waste+N+mask.png" />
        <image file="sea/sea+waste+N+E+mask.png" />
        <image file="sea/sea+waste+N+E+S+mask.png" />
        <image file="sea/sea+waste+N+E+S+W+mask.png" />
        <image file="sea/sea+waste+N+E+W+mask.png" />
        <image file="sea/sea+waste+N+S+mask.png" />
        <image file="sea/sea+waste+N+S+W+mask.png" />
        <image file="sea/sea+waste+N+W+mask.png" />
        <image file="sea/sea+waste+S+mask.png" />
        <image file="sea/sea+waste+S+W+mask.png" />
        <image file="sea/sea+waste+W+mask.png" />
        <image file="sea/sea+clear+E+mask.png" />
        <image file="sea/sea+clear+E+S+mask.png"  />
        <image file="sea/sea+clear+E+S+W+mask.png" />
        <image file="sea/sea+clear+E+W+mask.png" />
        <image file="sea/sea+clear+N+mask.png" />
        <image file="sea/sea+clear+N+E+mask.png" />
        <image file="sea/sea+clear+N+E+S+mask.png" />
        <image file="sea/sea+clear+N+E+S+W+mask.png" />
        <image file="sea/sea+clear+N+E+W+mask.png" />
        <image file="sea/sea+clear+N+S+mask.png" />
        <image file="sea/sea+clear+N+S+W+mask.png" />
        <image file="sea/sea+clear+N+W+mask.png" />
        <image file="sea/sea+clear+S+mask.png" />
        <image file="sea/sea+clear+S+W+mask.png" />
        <image file="sea/sea+clear+W+mask.png" />
        
        <image file="rough_sea+N+E+S+W+mask.png" cols = "4" />
        
        <image file="lake/lake+mask.png" cols = "8" />
        <image file="lake/lake+NE+mask.png" cols = "8" />
        <image file="lake/lake+NW+mask.png" cols = "8" />
        <image file="lake/lake+SE+mask.png" cols = "8" />
        <image file="lake/lake+SW+mask.png" cols = "8" />
        <image file="lake/lake+E+mask.png" cols = "8" />
        <image file="lake/lake+E+S+mask.png" cols = "8" />
        <image file="lake/lake+E+S+W+mask.png" cols = "8" />
        <image file="lake/lake+E+W+mask.png" cols = "8" />
        <image file="lake/lake+N+mask.png" cols = "8" />
        <image file="lake/lake+N+E+mask.png" cols = "8" />
        <image file="lake/lake+N+E+S+mask.png" cols = "8" />
        <image file="lake/lake+N+E+S+W+mask.png" cols = "8" />
        <image file="lake/lake+N+E+W+mask.png" cols = "8" />
        <image file="lake/lake+N+S+mask.png" cols = "8" />
        <image file="lake/lake+N+S+W+mask.png" cols = "8" />
        <image file="lake/lake+N+W+mask.png" cols = "8" />
        <image file="lake/lake+S+mask.png" cols = "8" />
        <image file="lake/lake+S+W+mask.png" cols = "8" />
        <image file="lake/lake+W+mask.png" cols = "8" />
        <image file="lake/lake+snow+E+S.png" />
        <image file="lake/lake+snow+E+S+W.png" />
        <image file="lake/lake+snow+N+E.png" />
        <image file="lake/lake+snow+N+E+S.png" />
        <image file="lake/lake+snow+N+E+S+W.png" />
        <image file="lake/lake+snow+N+E+W.png" />
        <image file="lake/lake+snow+N+S+W.png" />
        <image file="lake/lake+snow+N+W.png" />
        <image file="lake/lake+snow+S+W.png" />
        <image file="lake/lake+desert+E+S.png" />
        <image file="lake/lake+desert+E+S+W.png" />
        <image file="lake/lake+desert+N+E.png" />
        <image file="lake/lake+desert+N+E+S.png" />
        <image file="lake/lake+desert+N+E+S+W.png" />
        <image file="lake/lake+desert+N+E+W.png" />
        <image file="lake/lake+desert+N+S+W.png" />
        <image file="lake/lake+desert+N+W.png" />
        <image file="lake/lake+desert+S+W.png" />
        <image file="lake/lake+waste+E+S.png"  />
        <image file="lake/lake+waste+E+S+W.png" />
        <image file="lake/lake+waste+N+E.png" />
        <image file="lake/lake+waste+N+E+S.png" />
        <image file="lake/lake+waste+N+E+S+W.png" />
        <image file="lake/lake+waste+N+E+W.png" />
        <image file="lake/lake+waste+N+S+W.png" />
        <image file="lake/lake+waste+N+W.png" />
        <image file="lake/lake+waste+S+W.png" />
        <image file="lake/lake+clear+E+S.png"  />
        <image file="lake/lake+clear+E+S+W.png" />
        <image file="lake/lake+clear+N+E.png" />
        <image file="lake/lake+clear+N+E+S.png" />
        <image file="lake/lake+clear+N+E+S+W.png" />
        <image file="lake/lake+clear+N+E+W.png" />
        <image file="lake/lake+clear+N+S+W.png" />
        <image file="lake/lake+clear+N+W.png" />
        <image file="lake/lake+clear+S+W.png" />

        <image file="lake/riverend+W_lake+mask.png" cols = "8" />
        <image file="lake/riverend+W_lake+E+mask.png" cols = "8" />
        <image file="lake/riverend+W_lake+N+mask.png" cols = "8" />
        <image file="lake/riverend+W_lake+N+E+mask.png" cols = "8" />
        <image file="lake/riverend+W_lake+N+E+S+mask.png" cols = "8" />
        <image file="lake/riverend+W_lake+N+S+mask.png" cols = "8" />
        <image file="lake/riverend+W_lake+E+S+mask.png" cols = "8" />
        <image file="lake/riverend+W_lake+S+mask.png" cols = "8" />
        <image file="lake/riverend+S_lake+mask.png" cols = "8" />
        <image file="lake/riverend+S_lake+E+mask.png" cols = "8" />
        <image file="lake/riverend+S_lake+E+W+mask.png" cols = "8" />
        <image file="lake/riverend+S_lake+N+mask.png" cols = "8" />
        <image file="lake/riverend+S_lake+N+E+mask.png" cols = "8" />
        <image file="lake/riverend+S_lake+N+E+W+mask.png" cols = "8" />
        <image file="lake/riverend+S_lake+N+W+mask.png" cols = "8" />
        <image file="lake/riverend+S_lake+W+mask.png" cols = "8" />
        <image file="lake/riverend+N_lake+mask.png" cols = "8" />
        <image file="lake/riverend+N_lake+E+mask.png" cols = "8" />
        <image file="lake/riverend+N_lake+E+S+mask.png" cols = "8" />
        <image file="lake/riverend+N_lake+E+S+W+mask.png" cols = "8" />
        <image file="lake/riverend+N_lake+E+W+mask.png" cols = "8" />
        <image file="lake/riverend+N_lake+S+mask.png" cols = "8" />
        <image file="lake/riverend+N_lake+S+W+mask.png" cols = "8" />
        <image file="lake/riverend+N_lake+W+mask.png" cols = "8" />
        <image file="lake/riverend+E_lake+mask.png" cols = "8" />
        <image file="lake/riverend+E_lake+N+mask.png" cols = "8" />
        <image file="lake/riverend+E_lake+N+S+mask.png" cols = "8" />
        <image file="lake/riverend+E_lake+N+S+W+mask.png" cols = "8" />
        <image file="lake/riverend+E_lake+N+W+mask.png" cols = "8" />
        <image file="lake/riverend+E_lake+S+mask.png" cols = "8" />
        <image file="lake/riverend+E_lake+S+W+mask.png" cols = "8" />
        <image file="lake/riverend+E_lake+W+mask.png" cols = "8" />

        <!-- water falls -->
        <image file="river/riverend+N+1+mask.png" cols = "8" />
        <image file="river/riverend+E+1+mask.png" cols = "8" />
        <image file="river/riverend+S+1+mask.png" cols = "8" />
        <image file="river/riverend+W+1+mask.png" cols = "8" />
        <image file="river/riverend+N+1+land+W+mask.png" cols = "8" />
        <image file="river/riverend+E+1+land+N+mask.png" cols = "8" />
        <image file="river/riverend+S+1+land+W+mask.png" cols = "8" />
        <image file="river/riverend+W+1+land+N+mask.png" cols = "8" />
        <image file="river/riverend+N+1+land+N+mask.png" cols = "8" />
        <image file="river/riverend+W+1+land+W+mask.png" cols = "8" />
        <image file="river/riverend+N+1+land+N+W+mask.png" cols = "8" />
        <image file="river/riverend+W+1+land+N+W+mask.png" cols = "8" />
        <image file="river/riverend+N+1+land+NW+mask.png" cols = "8" />
        <image file="river/riverend+W+1+land+NW+mask.png" cols = "8" />
        <image file="river/riverend+N+2+mask.png" cols = "8" />
        <image file="river/riverend+E+2+mask.png" cols = "8" />
        <image file="river/riverend+S+2+mask.png" cols = "8" />
        <image file="river/riverend+W+2+mask.png" cols = "8" />
        <image file="river/riverend+S+2+land+E+mask.png" cols = "8" />
        <image file="river/riverend+E+2+land+E+mask.png" cols = "8" />
        <image file="river/riverend+E+2+land+N+mask.png" cols = "8" />
        <image file="river/riverend+N+2+land+E+mask.png" cols = "8" />
        <image file="river/riverend+N+2+land+N+mask.png" cols = "8" />
        <image file="river/riverend+W+2+land+N+mask.png" cols = "8" />
        <image file="river/riverend+E+2+land+N+E+mask.png" cols = "8" />
        <image file="river/riverend+N+2+land+N+E+mask.png" cols = "8" />
        <image file="river/riverend+N+2+land+NE+mask.png" cols = "8" />
        <image file="river/riverend+E+2+land+NE+mask.png" cols = "8" />
        <image file="river/riverend+N+3+mask.png" cols = "8" />
        <image file="river/riverend+E+3+mask.png" cols = "8" />
        <image file="river/riverend+S+3+mask.png" cols = "8" />
        <image file="river/riverend+W+3+mask.png" cols = "8" />
        <image file="river/riverend+E+3+land+E+mask.png" cols = "8" />
        <image file="river/riverend+N+3+land+E+mask.png" cols = "8" />
        <image file="river/riverend+S+3+land+E+mask.png" cols = "8" />
        <image file="river/riverend+S+3+land+S+mask.png" cols = "8" />
        <image file="river/riverend+W+3+land+S+mask.png" cols = "8" />
        <image file="river/riverend+E+3+land+S+mask.png" cols = "8" />
        <image file="river/riverend+S+3+land+E+S+mask.png" cols = "8" />
        <image file="river/riverend+E+3+land+E+S+mask.png" cols = "8" />
        <image file="river/riverend+S+3+land+SE+mask.png" cols = "8" />
        <image file="river/riverend+E+3+land+SE+mask.png" cols = "8" />
        <image file="river/riverend+N+4+mask.png" cols = "8" />
        <image file="river/riverend+E+4+mask.png" cols = "8" />
        <image file="river/riverend+S+4+mask.png" cols = "8" />
        <image file="river/riverend+W+4+mask.png" cols = "8" />
        <image file="river/riverend+S+4+land+W+mask.png" cols = "8" />
        <image file="river/riverend+E+4+land+S+mask.png" cols = "8" />
        <image file="river/riverend+N+4+land+W+mask.png" cols = "8" />
        <image file="river/riverend+S+4+land+S+mask.png" cols = "8" />
        <image file="river/riverend+W+4+land+S+mask.png" cols = "8" />
        <image file="river/riverend+W+4+land+W+mask.png" cols = "8" />
        <image file="river/riverend+S+4+land+S+W+mask.png" cols = "8" />
        <image file="river/riverend+W+4+land+S+W+mask.png" cols = "8" />
        <image file="river/riverend+W+4+land+SW+mask.png" cols = "8" />
        <image file="river/riverend+S+4+land+SW+mask.png" cols = "8" />

        <image file="fire.png" cols = "6" />

        <image file="reaf/reaf+E+mask.png" cols = "8" />
        <image file="reaf/reaf+N+mask.png" cols = "8" />
        <image file="reaf/reaf+S+mask.png" cols = "8" />
        <image file="reaf/reaf+W+mask.png" cols = "8" />        
        <image file="reaf/reaf+E+S+mask.png" cols = "8" />
        <image file="reaf/reaf+S+W+mask.png" cols = "8" />
        <image file="reaf/reaf+N+W+mask.png" cols = "8" />
        <image file="reaf/reaf+N+E+mask.png" cols = "8" />
        
        <image file="reaf/reaf+E+W+mask.png" cols = "8" />
        <image file="reaf/reaf+N+S+mask.png" cols = "8" />
        
        <image file="reaf/reaf+N+E+S+W+mask.png" cols = "8" />
        <image file="reaf/reaf+E+S+W+mask.png" cols = "8" />
        <image file="reaf/reaf+N+E+S+mask.png" cols = "8" />        
        <image file="reaf/reaf+N+E+W+mask.png" cols = "8" />
        <image file="reaf/reaf+N+S+W+mask.png" cols = "8" />
        <image file="reaf/reaf+NE+NW+S+mask.png" cols = "8" />
        <image file="reaf/reaf+NE+NW+mask.png" cols = "8" />
        <image file="reaf/reaf+NE+S+W+mask.png" cols = "8" />
        <image file="reaf/reaf+NE+S+mask.png" cols = "8" />
        <image file="reaf/reaf+NE+W+mask.png" cols = "8" />
        <image file="reaf/reaf+NE+mask.png" cols = "8" />
        <image file="reaf/reaf+NW+E+mask.png" cols = "8" />
        <image file="reaf/reaf+NW+S+E+mask.png" cols = "8" />
        <image file="reaf/reaf+NW+S+mask.png" cols = "8" />
        <image file="reaf/reaf+NW+mask.png" cols = "8" />
        
        <image file="mountain/mountain.png" />
        <image file="mountain/mountain+short.png" />
        
        <image file="fog/fog+mask.png" />
        <image file="fog/fog+E+mask.png" />
        <image file="fog/fog+E+W+mask.png" />
        <image file="fog/fog+W+mask.png" />
        <image file="fog/fog+NW+mask.png" />
        <image file="fog/fog+NE+mask.png" />
        <image file="fog/fog+SW+mask.png" />
        <image file="fog/fog+SE+mask.png" />
        
        <image file="beach/beach+E+land+N+mask.png" cols = "8" />
        <image file="beach/beach+E+land+N+S+mask.png" cols = "8" />
        <image file="beach/beach+E+land+N+S+W+mask.png" cols = "8" />
        <image file="beach/beach+E+land+N+W+mask.png" cols = "8" />
        <image file="beach/beach+E+land+S+mask.png" cols = "8" />
        <image file="beach/beach+E+land+S+W+mask.png" cols = "8" />
        <image file="beach/beach+E+S+land+N+W+mask.png" cols = "8" />
        <image file="beach/beach+E+W+land+N+mask.png" cols = "8" />
        <image file="beach/beach+E+W+land+N+S+mask.png" cols = "8" />
        <image file="beach/beach+E+W+land+S+mask.png" cols = "8" />
        <image file="beach/beach+land+E+mask.png" cols = "8" />
        <image file="beach/beach+land+E+S+mask.png" cols = "8" />
        <image file="beach/beach+land+E+S+W+mask.png" cols = "8" />
        <image file="beach/beach+land+E+W+mask.png" cols = "8" />
        <image file="beach/beach+land+N+mask.png" cols = "8" />
        <image file="beach/beach+land+N+E+mask.png" cols = "8" />
        <image file="beach/beach+land+N+E+S+mask.png" cols = "8" />
        <image file="beach/beach+land+N+E+S+W+mask.png" cols = "8" />
        <image file="beach/beach+land+N+E+W+mask.png" cols = "8" />
        <image file="beach/beach+land+N+S+mask.png" cols = "8" />
        <image file="beach/beach+land+N+S+W+mask.png" cols = "8" />
        <image file="beach/beach+land+N+W+mask.png" cols = "8" />
        <image file="beach/beach+land+S+mask.png" cols = "8" />
        <image file="beach/beach+land+S+W+mask.png" cols = "8" />
        <image file="beach/beach+land+W+mask.png" cols = "8" />
        <image file="beach/beach+land+SW+mask.png" cols = "8" />
        <image file="beach/beach+land+NW+mask.png" cols = "8" />
        <image file="beach/beach+land+NE+mask.png" cols = "8" />
        <image file="beach/beach+land+SE+mask.png" cols = "8" />
        <image file="beach/beach+W+land+SW+mask.png" cols = "8" />
        <image file="beach/beach+W+land+NW+mask.png" cols = "8" />
        <image file="beach/beach+S+land+SW+mask.png" cols = "8" />
        <image file="beach/beach+S+land+SE+mask.png" cols = "8" />
        <image file="beach/beach+S+W+land+SW+mask.png" cols = "8" />
        <image file="beach/beach+N+land+NE+mask.png" cols = "8" />
        <image file="beach/beach+N+land+NW+mask.png" cols = "8" />
        <image file="beach/beach+N+W+land+NW+mask.png" cols = "8" />
        <image file="beach/beach+N+E+land+NE+mask.png" cols = "8" />
        <image file="beach/beach+E+land+NE+mask.png" cols = "8" />
        <image file="beach/beach+E+land+SE+mask.png" cols = "8" />
        <image file="beach/beach+E+S+land+SE+mask.png" cols = "8" />
        <image file="beach/beach+N+E+land+S+W+mask.png" cols = "8" />
        <image file="beach/beach+N+land+E+mask.png" cols = "8" />
        <image file="beach/beach+N+land+E+S+W+mask.png" cols = "8" />
        <image file="beach/beach+N+land+E+W+mask.png" cols = "8" />
        <image file="beach/beach+N+land+E+S+mask.png" cols = "8" />
        <image file="beach/beach+N+land+S+W+mask.png" cols = "8" />
        <image file="beach/beach+N+land+W+mask.png" cols = "8" />
        <image file="beach/beach+N+S+land+E+mask.png" cols = "8" />
        <image file="beach/beach+N+S+land+E+W+mask.png" cols = "8" />
        <image file="beach/beach+N+S+land+W+mask.png" cols = "8" />
        <image file="beach/beach+N+W+land+E+S+mask.png" cols = "8" />
        <image file="beach/beach+S+land+E+mask.png" cols = "8" />
        <image file="beach/beach+S+land+W+mask.png" cols = "8" />
        <image file="beach/beach+S+land+E+W+mask.png" cols = "8" />
        <image file="beach/beach+S+land+N+E+mask.png" cols = "8" />
        <image file="beach/beach+S+land+N+E+W+mask.png" cols = "8" />
        <image file="beach/beach+S+land+N+W+mask.png" cols = "8" />
        <image file="beach/beach+W+land+E+S+mask.png" cols = "8" />
        <image file="beach/beach+W+land+N+mask.png" cols = "8" />
        <image file="beach/beach+W+land+N+E+mask.png" cols = "8" />
        <image file="beach/beach+S+W+land+N+E+mask.png" cols = "8" />
        <image file="beach/beach+W+land+N+E+S+mask.png" cols = "8" />
        <image file="beach/beach+W+land+N+S+mask.png" cols = "8" />
        <image file="beach/beach+W+land+S+mask.png" cols = "8" />
        <image file="beach/beach+mask.png" cols = "8" />
        <image file="beach/beach+E+mask.png" cols = "8" />
        <image file="beach/beach+E+S+mask.png" cols = "8" />
        <image file="beach/beach+E+S+W+mask.png" cols = "8" />
        <image file="beach/beach+N+mask.png" cols = "8" />
        <image file="beach/beach+N+E+mask.png" cols = "8" />
        <image file="beach/beach+N+E+S+mask.png" cols = "8" />
        <image file="beach/beach+N+E+S+W+mask.png" cols = "8" />
        <image file="beach/beach+N+E+S+W+sea+NE+mask.png" cols = "8" />
        <image file="beach/beach+N+E+S+W+sea+NW+mask.png" cols = "8" />
        <image file="beach/beach+N+E+S+W+sea+SE+mask.png" cols = "8" />
        <image file="beach/beach+N+E+S+W+sea+SW+mask.png" cols = "8" />
        <image file="beach/beach+N+E+W+mask.png" cols = "8" />
        <image file="beach/beach+N+S+W+mask.png" cols = "8" />
        <image file="beach/beach+N+W+mask.png" cols = "8" />
        <image file="beach/beach+S+mask.png" cols = "8" />
        <image file="beach/beach+S+W+mask.png" cols = "8" />
        <image file="beach/beach+W+mask.png" cols = "8" />
        <image file="beach/beach+N+S+mask.png" cols = "8" />
        <image file="beach/beach+E+W+mask.png" cols = "8" />
        <image file="beach/beach+overlay+W+mask.png" cols = "8" />
        <image file="beach/beach+overlay+E+mask.png" cols = "8" />
        <image file="beach/beach+overlay+S+mask.png" cols = "8" />
        <image file="beach/beach+overlay+N+mask.png" cols = "8" />
        <image file="beach/beach+land+SW+overlay+mask.png" cols = "8" />
        <image file="beach/beach+land+SE+overlay+mask.png" cols = "8" />
        <image file="beach/beach+land+NW+overlay+mask.png" cols = "8" />
        <image file="beach/beach+land+NE+overlay+mask.png" cols = "8" />

        <image file="ruins/ruin+0.png" />
        <image file="ruins/ruin+1.png" />
        <image file="ruins/ruin+2.png" />
        
        <!-- forest -->
        <image file="forest/forest_style0.png" />
        <image file="forest/forest_style0+E.png" />
        <image file="forest/forest_style0+E+W.png" />
        <image file="forest/forest_style0+W.png" />
        <image file="forest/forest_style0+NE.png" />
        <image file="forest/forest_style0+NW.png" />
        <image file="forest/forest_style0+SE.png" />
        <image file="forest/forest_style0+SW.png" />        
        <image file="forest/forest_style1.png" />
        <image file="forest/forest_style1+E.png" />
        <image file="forest/forest_style1+E+W.png" />
        <image file="forest/forest_style1+W.png" />
        <image file="forest/forest_style1+NE.png" />
        <image file="forest/forest_style1+NW.png" />
        <image file="forest/forest_style1+SE.png" />
        <image file="forest/forest_style1+SW.png" />        
        <image file="forest/forest_style2.png" />
        <image file="forest/forest_style2+E.png" />
        <image file="forest/forest_style2+E+W.png" />
        <image file="forest/forest_style2+W.png" />
        <image file="forest/forest_style2+NE.png" />
        <image file="forest/forest_style2+NW.png" />
        <image file="forest/forest_style2+SE.png" />
        <image file="forest/forest_style2+SW.png" />        
        <image file="forest/forest_style3.png" />
        <image file="forest/forest_style3+E.png" />
        <image file="forest/forest_style3+E+W.png" />
        <image file="forest/forest_style3+W.png" />
        <image file="forest/forest_style3+NE.png" />
        <image file="forest/forest_style3+NW.png" />
        <image file="forest/forest_style3+SE.png" />
        <image file="forest/forest_style3+SW.png" />
        
        <image file="wasteland/wasteland+0.png" />
        <image file="wasteland/wasteland+1.png" />
        <image file="wasteland/wasteland+2.png" />
        <image file="wasteland/wasteland+3.png" />
        <image file="wasteland/wasteland+4.png" />
        <image file="wasteland/wasteland+5.png" />
        
        <image file="street/street+style0.png" />
        <image file="street/street+style0+E.png" />
        <image file="street/street+style0+E+S.png" />
        <image file="street/street+style0+E+S+W.png" />
        <image file="street/street+style0+E+W.png" />
        <image file="street/street+style0+N.png" />
        <image file="street/street+style0+N+E.png" />
        <image file="street/street+style0+N+E+S.png" />
        <image file="street/street+style0+N+E+S+W.png" />
        <image file="street/street+style0+N+E+W.png" />
        <image file="street/street+style0+N+S.png" />
        <image file="street/street+style0+N+S+W.png" />
        <image file="street/street+style0+N+W.png" />
        <image file="street/street+style0+S.png" />
        <image file="street/street+style0+S+W.png" />
        <image file="street/street+style0+W.png" />
        <image file="street/street+style0+shadow.png" />
        <image file="street/street+style0+E+shadow.png" />
        <image file="street/street+style0+E+S+shadow.png" />
        <image file="street/street+style0+E+S+W+shadow.png" />
        <image file="street/street+style0+E+W+shadow.png" />
        <image file="street/street+style0+N+shadow.png" />
        <image file="street/street+style0+N+E+shadow.png" />
        <image file="street/street+style0+N+E+S+shadow.png" />
        <image file="street/street+style0+N+E+S+W+shadow.png" />
        <image file="street/street+style0+N+E+W+shadow.png" />
        <image file="street/street+style0+N+S+shadow.png" />
        <image file="street/street+style0+N+S+W+shadow.png" />
        <image file="street/street+style0+N+W+shadow.png" />
        <image file="street/street+style0+S+shadow.png" />
        <image file="street/street+style0+S+W+shadow.png" />
        <image file="street/street+style0+W+shadow.png" />
        <image file="street/street+style1.png" />
        <image file="street/street+style1+E.png" />
        <image file="street/street+style1+E+S.png" />
        <image file="street/street+style1+E+S+W.png" />
        <image file="street/street+style1+E+W.png" />
        <image file="street/street+style1+N.png" />
        <image file="street/street+style1+N+E.png" />
        <image file="street/street+style1+N+E+S.png" />
        <image file="street/street+style1+N+E+S+W.png" />
        <image file="street/street+style1+N+E+W.png" />
        <image file="street/street+style1+N+S.png" />
        <image file="street/street+style1+N+S+W.png" />
        <image file="street/street+style1+N+W.png" />
        <image file="street/street+style1+S.png" />
        <image file="street/street+style1+S+W.png" />
        <image file="street/street+style1+W.png" />
        <image file="street/street+style1+shadow.png" />
        <image file="street/street+style1+E+shadow.png" />
        <image file="street/street+style1+E+S+shadow.png" />
        <image file="street/street+style1+E+S+W+shadow.png" />
        <image file="street/street+style1+E+W+shadow.png" />
        <image file="street/street+style1+N+shadow.png" />
        <image file="street/street+style1+N+E+shadow.png" />
        <image file="street/street+style1+N+E+S+shadow.png" />
        <image file="street/street+style1+N+E+S+W+shadow.png" />
        <image file="street/street+style1+N+E+W+shadow.png" />
        <image file="street/street+style1+N+S+shadow.png" />
        <image file="street/street+style1+N+S+W+shadow.png" />
        <image file="street/street+style1+N+W+shadow.png" />
        <image file="street/street+style1+S+shadow.png" />
        <image file="street/street+style1+S+W+shadow.png" />
        <image file="street/street+style1+W+shadow.png" />

        <!-- creeper -->
        <image file="creeper/creeper.png" />
        <image file="creeper/creeper+E.png" />
        <image file="creeper/creeper+E+W.png" />
        <image file="creeper/creeper+W.png" />
        <image file="creeper/creeper+SE.png" />
        <image file="creeper/creeper+NE.png" />
        <image file="creeper/creeper+SW.png" />
        <image file="creeper/creeper+NW.png" />
        
        <!-- river -->
        <image file="river/river+0+land+N+E+S+W+mask.png" cols = "8" />
        <image file="river/river+1+land+N+E+S+W+mask.png" cols = "8" />
        <image file="river/river+land+E+S+W+mask.png" cols = "8" />
        <image file="river/river+land+N+E+S+mask.png" cols = "8" />
        <image file="river/river+land+N+E+W+mask.png" cols = "8" />
        <image file="river/river+land+N+S+W+mask.png" cols = "8" />
        <image file="river/river+S+W+land+N+W+mask.png" cols = "8" />
        <image file="river/river+S+W+land+N+W+SE+mask.png" cols = "8" />
        <image file="river/river+E+S+land+N+E+mask.png" cols = "8" />
        <image file="river/river+N+W+land+S+W+NE+mask.png" cols = "8" />
        <image file="river/river+E+land+N+S+W+mask.png" cols = "8" />
        <image file="river/river+E+land+N+W+mask.png" cols = "8" />
        <image file="river/river+E+land+N+W+SE+mask.png" cols = "8" />
        <image file="river/river+E+land+S+W+mask.png" cols = "8" />
        <image file="river/river+E+land+S+W+NE+mask.png" cols = "8" />
        <image file="river/river+E+S+land+W+NE+mask.png" cols = "8" />
        <image file="river/river+N+land+E+NW+SW+mask.png" cols = "8" />
        <image file="river/river+N+land+E+S+mask.png" cols = "8" />
        <image file="river/river+N+land+E+S+NW+mask.png" cols = "8" />
        <image file="river/river+N+land+E+S+W+mask.png" cols = "8" />
        <image file="river/river+N+land+S+W+mask.png" cols = "8" />
        <image file="river/river+N+W+land+E+NW+SW+mask.png" cols = "8" />
        <image file="river/river+S+land+E+NW+SW+mask.png" cols = "8" />
        <image file="river/river+S+land+N+E+SW+mask.png" cols = "8" />
        <image file="river/river+S+land+N+E+W+mask.png" cols = "8" />
        <image file="river/river+S+W+land+E+NW+SW+mask.png" cols = "8" />
        <image file="river/river+W+land+E+S+mask.png" cols = "8" />
        <image file="river/river+S+land+E+W+mask.png" cols = "8" />
        <image file="river/river+N+land+E+W+mask.png" cols = "8" />
        <image file="river/river+E+land+N+S+mask.png" cols = "8" />
        <image file="river/river+W+land+N+S+mask.png" cols = "8" />
        <image file="river/river+S+land+E+W+bridge+mask.png" cols = "8" />
        <image file="river/river+E+land+N+SE+mask.png" cols = "8" />
        <image file="river/river+E+land+S+NE+mask.png" cols = "8" />
        <image file="river/river+E+land+S+NE+NW+mask.png" cols = "8" />
        <image file="river/river+W+land+S+NW+mask.png" cols = "8" />
        <image file="river/river+W+land+N+SW+mask.png" cols = "8" />
        <image file="river/river+E+land+S+mask.png" cols = "8" />
        <image file="river/river+E+land+N+mask.png" cols = "8" />
        <image file="river/river+E+mask.png" cols = "8" />
        <image file="river/river+W+mask.png" cols = "8" />
        <image file="river/river+N+mask.png" cols = "8" />
        <image file="river/river+S+mask.png" cols = "8" />
        <image file="river/river+N+land+W+mask.png" cols = "8" />
        <image file="river/river+N+land+W+NE+SE+mask.png" cols = "8" />
        <image file="river/river+E+S+land+N+SE+SW+mask.png" cols = "8" />
        <image file="river/river+E+S+land+N+SW+mask.png" cols = "8" />
        <image file="river/river+E+S+land+W+NE+SE+mask.png" cols = "8" />
        <image file="river/river+E+W+land+S+NE+NW+mask.png" cols = "8" />
        <image file="river/river+N+E+land+S+NE+NW+mask.png" cols = "8" />
        <image file="river/river+N+E+land+S+NW+mask.png" cols = "8" />
        <image file="river/river+N+E+land+W+NE+SE+mask.png" cols = "8" />
        <image file="river/river+N+E+land+W+SE+mask.png" cols = "8" />
        <image file="river/river+N+land+E+mask.png" cols = "8" />
        <image file="river/river+N+land+E+NW+mask.png" cols = "8" />
        <image file="river/river+N+land+E+SW+NW+mask.png" cols = "8" />
        <image file="river/river+N+land+W+NE+mask.png" cols = "8" />
        <image file="river/river+N+W+land+E+SW+mask.png" cols = "8" />
        <image file="river/river+N+W+land+E+SW+NW+mask.png" cols = "8" />
        <image file="river/river+N+W+land+S+NE+mask.png" cols = "8" />
        <image file="river/river+N+W+land+S+NE+NW+mask.png" cols = "8" />
        <image file="river/river+S+land+E+mask.png" cols = "8" />
        <image file="river/river+S+land+E+SW+mask.png" cols = "8" />
        <image file="river/river+S+land+E+SW+NW+mask.png" cols = "8" />
        <image file="river/river+S+land+N+SE+SW+mask.png" cols = "8" />
        <image file="river/river+S+land+NE+SE+SW+NW+mask.png" cols = "8" />
        <image file="river/river+S+land+W+mask.png" cols = "8" />
        <image file="river/river+S+land+W+NE+SE+mask.png" cols = "8" />
        <image file="river/river+S+land+W+SE+mask.png" cols = "8" />
        <image file="river/river+S+W+land+E+NW+mask.png" cols = "8" />
        <image file="river/river+S+W+land+E+SW+NW+mask.png" cols = "8" />
        <image file="river/river+S+W+land+N+SE+mask.png" cols = "8" />
        <image file="river/river+S+W+land+N+SE+SW+mask.png" cols = "8" />
        <image file="river/river+W+land+N+mask.png" cols = "8" />
        <image file="river/river+W+land+S+mask.png" cols = "8" />
        <image file="river/river+W+land+S+NE+NW+mask.png" cols = "8" />
        <image file="river/river+W+land+E+S+NW+mask.png" cols = "8" />
        <image file="river/river+W+land+N+E+mask.png" cols = "8" />
        <image file="river/river+W+land+N+E+S+mask.png" cols = "8" />
        <image file="river/river+W+land+N+E+SW+mask.png" cols = "8" />

        <!-- plasma -->
        <image file="plasma/plasma.png" cols = "3" />
        <image file="plasma/plasma+E.png" cols = "3" />
        <image file="plasma/plasma+E+S.png" cols = "3" />
        <image file="plasma/plasma+E+S+W.png" cols = "3" />
        <image file="plasma/plasma+E+W.png" cols = "3" />
        <image file="plasma/plasma+N.png" cols = "3" />
        <image file="plasma/plasma+N+E.png" cols = "3" />
        <image file="plasma/plasma+N+E+S.png" cols = "3" />
        <image file="plasma/plasma+N+E+S+W.png" cols = "3" />
        <image file="plasma/plasma+N+E+W.png" cols = "3" />
        <image file="plasma/plasma+N+S.png" cols = "3" />
        <image file="plasma/plasma+N+S+W.png" cols = "3" />
        <image file="plasma/plasma+N+W.png" cols = "3" />
        <image file="plasma/plasma+S.png" cols = "3" />
        <image file="plasma/plasma+S+W.png" cols = "3" />
        <image file="plasma/plasma+W.png" cols = "3" />
        
        <image file="meteor/meteor.png" cols = "3" />
        <image file="meteor/meteor+E.png" cols = "3" />
        <image file="meteor/meteor+E+S.png" cols = "3" />
        <image file="meteor/meteor+E+S+W.png" cols = "3" />
        <image file="meteor/meteor+E+W.png" cols = "3" />
        <image file="meteor/meteor+S.png" cols = "3" />
        <image file="meteor/meteor+S+W.png" cols = "3" />
        <image file="meteor/meteor+W.png" cols = "3" />
        
        <image file="pipeline/pipeline.png" />
        <image file="pipeline/pipeline+E.png" />
        <image file="pipeline/pipeline+E+S.png" />
        <image file="pipeline/pipeline+E+S+W.png" />
        <image file="pipeline/pipeline+E+W.png" />
        <image file="pipeline/pipeline+N.png" />
        <image file="pipeline/pipeline+N+E.png" />
        <image file="pipeline/pipeline+N+E+S.png" />
        <image file="pipeline/pipeline+N+E+S+W.png" />
        <image file="pipeline/pipeline+N+E+W.png" />
        <image file="pipeline/pipeline+N+S.png" />
        <image file="pipeline/pipeline+N+S+W.png" />
        <image file="pipeline/pipeline+N+W.png" />
        <image file="pipeline/pipeline+S.png" />
        <image file="pipeline/pipeline+S+W.png" />
        <image file="pipeline/pipeline+W.png" />
        <image file="pipeline/weld+E+W.png" />
        <image file="pipeline/weld+N+S.png" />        
        <image file="pipeline/destroyedweld+E+W.png" />
        <image file="pipeline/destroyedweld+N+S.png" />
        
        <image file="wall/wall.png" />
        <image file="wall/wall+E.png" />
        <image file="wall/wall+E+S.png" />
        <image file="wall/wall+E+S+W.png" />
        <image file="wall/wall+E+W.png" />
        <image file="wall/wall+N.png" />
        <image file="wall/wall+N+E.png" />
        <image file="wall/wall+N+E+S.png" />
        <image file="wall/wall+N+E+S+W.png" />
        <image file="wall/wall+N+E+W.png" />
        <image file="wall/wall+N+S.png" />
        <image file="wall/wall+N+S+W.png" />
        <image file="wall/wall+N+W.png" />
        <image file="wall/wall+S.png" />
        <image file="wall/wall+S+W.png" />
        <image file="wall/wall+W.png" />
        <image file="wall/weak_wall+E+W.png" />
        <image file="wall/weak_wall+N+S.png" />
        
        <image file="bridge/bridge+style0.png" />
        <image file="bridge/bridge+style0+E.png" />
        <image file="bridge/bridge+style0+E+S.png" />
        <image file="bridge/bridge+style0+E+S+W.png" />
        <image file="bridge/bridge+style0+E+W.png" />
        <image file="bridge/bridge+style0+N.png" />
        <image file="bridge/bridge+style0+N+E.png" />
        <image file="bridge/bridge+style0+N+E+S.png" />
        <image file="bridge/bridge+style0+N+E+S+W.png" />
        <image file="bridge/bridge+style0+N+E+W.png" />
        <image file="bridge/bridge+style0+N+S.png" />
        <image file="bridge/bridge+style0+N+S+W.png" />
        <image file="bridge/bridge+style0+N+W.png" />
        <image file="bridge/bridge+style0+S.png" />
        <image file="bridge/bridge+style0+S+W.png" />
        <image file="bridge/bridge+style0+W.png" />
        <image file="bridge/bridge+style1.png" />
        <image file="bridge/bridge+style1+E.png" />
        <image file="bridge/bridge+style1+E+S.png" />
        <image file="bridge/bridge+style1+E+S+W.png" />
        <image file="bridge/bridge+style1+E+W.png" />
        <image file="bridge/bridge+style1+N.png" />
        <image file="bridge/bridge+style1+N+E.png" />
        <image file="bridge/bridge+style1+N+E+S.png" />
        <image file="bridge/bridge+style1+N+E+S+W.png" />
        <image file="bridge/bridge+style1+N+E+W.png" />
        <image file="bridge/bridge+style1+N+S.png" />
        <image file="bridge/bridge+style1+N+S+W.png" />
        <image file="bridge/bridge+style1+N+W.png" />
        <image file="bridge/bridge+style1+S.png" />
        <image file="bridge/bridge+style1+S+W.png" />
        <image file="bridge/bridge+style1+W.png" />        
        <image file="bridge/bridge_river.png" />
        <image file="bridge/bridge_river+E.png" />
        <image file="bridge/bridge_river+E+S.png" />
        <image file="bridge/bridge_river+E+S+W.png" />
        <image file="bridge/bridge_river+E+W.png" />
        <image file="bridge/bridge_river+N.png" />
        <image file="bridge/bridge_river+N+E.png" />
        <image file="bridge/bridge_river+N+E+S.png" />
        <image file="bridge/bridge_river+N+E+S+W.png" />
        <image file="bridge/bridge_river+N+E+W.png" />
        <image file="bridge/bridge_river+N+S.png" />
        <image file="bridge/bridge_river+N+S+W.png" />
        <image file="bridge/bridge_river+N+W.png" />
        <image file="bridge/bridge_river+S.png" />
        <image file="bridge/bridge_river+S+W.png" />
        <image file="bridge/bridge_river+W.png" />
        
        <!-- Snowy Stuff praise Olaf -->
        <image file="snow/snow+0.png" />
        <image file="snow/snow+1.png" />
        <image file="snow/snow+2.png" />
        <image file="snow/snow+3.png" />
        <image file="snow/snow+4.png" />
        <image file="snow/snow+5.png" />
        <image file="snow/snow+6.png" />
        <image file="snow/snow+7.png" />
        <image file="snow/snow+8.png" />
        <image file="snow/snow+9.png" />
        <image file="snow/snow+10.png" />
        <image file="snow/snow+11.png" />
        <image file="snow/snow+12.png" />
        <image file="snow/snow+13.png" />
        <image file="snow/snow+14.png" />
        <image file="snow/snow+15.png" />
        <image file="snow/snow+16.png" />
        <image file="snow/snow+17.png" />
        <image file="snow/snow+18.png" />
        <image file="snow/snow+19.png" />
        <image file="snow/snow+20.png" />
        <image file="snow/snow+21.png" />
        <image file="snow/snow+W.png" />
        <image file="snow/snow+S.png" />
        <image file="snow/snow+E.png" />
        <image file="snow/snow+N.png" />
        <image file="snow/shadow_snow.png" />

        <image file="snow_forest/snow_forest+style0.png" />
        <image file="snow_forest/snow_forest+style0+E.png" />
        <image file="snow_forest/snow_forest+style0+E+W.png" />
        <image file="snow_forest/snow_forest+style0+W.png" />
        <image file="snow_forest/snow_forest+style0+SE.png" />
        <image file="snow_forest/snow_forest+style0+NE.png" />
        <image file="snow_forest/snow_forest+style0+SW.png" />
        <image file="snow_forest/snow_forest+style0+NW.png" />
        <image file="snow_forest/snow_forest+style1.png" />
        <image file="snow_forest/snow_forest+style1+E.png" />
        <image file="snow_forest/snow_forest+style1+E+W.png" />
        <image file="snow_forest/snow_forest+style1+W.png" />
        <image file="snow_forest/snow_forest+style1+SE.png" />
        <image file="snow_forest/snow_forest+style1+NE.png" />
        <image file="snow_forest/snow_forest+style1+SW.png" />
        <image file="snow_forest/snow_forest+style1+NW.png" />
        <image file="snow_forest/snow_forest+style2.png" />
        <image file="snow_forest/snow_forest+style2+E.png" />
        <image file="snow_forest/snow_forest+style2+E+W.png" />
        <image file="snow_forest/snow_forest+style2+W.png" />
        <image file="snow_forest/snow_forest+style2+SE.png" />
        <image file="snow_forest/snow_forest+style2+NE.png" />
        <image file="snow_forest/snow_forest+style2+SW.png" />
        <image file="snow_forest/snow_forest+style2+NW.png" />

        <image file="wasteland/snow_wasteland+0.png" />
        <image file="wasteland/snow_wasteland+1.png" />
        <image file="wasteland/snow_wasteland+2.png" />
        <image file="wasteland/snow_wasteland+3.png" />
        <image file="wasteland/snow_wasteland+4.png" />
        <image file="wasteland/snow_wasteland+5.png" />

        <image file="mountain/snow_mountain.png" />
        <image file="mountain/snow_mountain+short.png" />
        
        <image file="snow_Pipeline/snow_destroyedweld+E+W.png" />
        <image file="snow_Pipeline/snow_destroyedweld+N+S.png" />        
        <image file="snow_Pipeline/snow_weld+E+W.png" />
        <image file="snow_Pipeline/snow_weld+N+S.png" />        
        <image file="snow_Pipeline/snow_Pipeline.png" />
        <image file="snow_Pipeline/snow_Pipeline+E.png" />
        <image file="snow_Pipeline/snow_Pipeline+E+S.png" />
        <image file="snow_Pipeline/snow_Pipeline+E+S+W.png" />
        <image file="snow_Pipeline/snow_Pipeline+E+W.png" />
        <image file="snow_Pipeline/snow_Pipeline+N.png" />
        <image file="snow_Pipeline/snow_Pipeline+N+E.png" />
        <image file="snow_Pipeline/snow_Pipeline+N+E+S.png" />
        <image file="snow_Pipeline/snow_Pipeline+N+E+S+W.png" />
        <image file="snow_Pipeline/snow_Pipeline+N+E+W.png" />
        <image file="snow_Pipeline/snow_Pipeline+N+S.png" />
        <image file="snow_Pipeline/snow_Pipeline+N+S+W.png" />
        <image file="snow_Pipeline/snow_Pipeline+N+W.png" />
        <image file="snow_Pipeline/snow_Pipeline+S.png" />
        <image file="snow_Pipeline/snow_Pipeline+S+W.png" />
        <image file="snow_Pipeline/snow_Pipeline+W.png" />
        
        <image file="ruins/snow_ruin+0.png" />
        <image file="ruins/snow_ruin+1.png" />
        <image file="ruins/snow_ruin+2.png" />

        <image file="snow_street/snow_street+style0.png" />
        <image file="snow_street/snow_street+style0+E.png" />
        <image file="snow_street/snow_street+style0+E+S.png" />
        <image file="snow_street/snow_street+style0+E+S+W.png" />
        <image file="snow_street/snow_street+style0+E+W.png" />
        <image file="snow_street/snow_street+style0+N.png" />
        <image file="snow_street/snow_street+style0+N+E.png" />
        <image file="snow_street/snow_street+style0+N+E+S.png" />
        <image file="snow_street/snow_street+style0+N+E+S+W.png" />
        <image file="snow_street/snow_street+style0+N+E+W.png" />
        <image file="snow_street/snow_street+style0+N+S.png" />
        <image file="snow_street/snow_street+style0+N+S+W.png" />
        <image file="snow_street/snow_street+style0+N+W.png" />
        <image file="snow_street/snow_street+style0+S.png" />
        <image file="snow_street/snow_street+style0+S+W.png" />
        <image file="snow_street/snow_street+style0+W.png" />
        <image file="snow_street/snow_street+style0+shadow.png" />
        <image file="snow_street/snow_street+style0+E+shadow.png" />
        <image file="snow_street/snow_street+style0+E+S+shadow.png" />
        <image file="snow_street/snow_street+style0+E+S+W+shadow.png" />
        <image file="snow_street/snow_street+style0+E+W+shadow.png" />
        <image file="snow_street/snow_street+style0+N+shadow.png" />
        <image file="snow_street/snow_street+style0+N+E+shadow.png" />
        <image file="snow_street/snow_street+style0+N+E+S+shadow.png" />
        <image file="snow_street/snow_street+style0+N+E+S+W+shadow.png" />
        <image file="snow_street/snow_street+style0+N+E+W+shadow.png" />
        <image file="snow_street/snow_street+style0+N+S+shadow.png" />
        <image file="snow_street/snow_street+style0+N+S+W+shadow.png" />
        <image file="snow_street/snow_street+style0+N+W+shadow.png" />
        <image file="snow_street/snow_street+style0+S+shadow.png" />
        <image file="snow_street/snow_street+style0+S+W+shadow.png" />
        <image file="snow_street/snow_street+style0+W+shadow.png" />

        <!-- desert stuff here comes zandra -->
        <image file="desert/desert+0.png" />
        <image file="desert/desert+1.png" />
        <image file="desert/desert+2.png" />
        <image file="desert/desert+3.png" />
        <image file="desert/desert+4.png" />
        <image file="desert/desert+5.png" />
        <image file="desert/desert+6.png" />
        <image file="desert/desert+7.png" />
        <image file="desert/desert+8.png" />
        <image file="desert/desert+9.png" />
        <image file="desert/desert+10.png" />
        <image file="desert/desert+11.png" />
        <image file="desert/desert+12.png" />
        <image file="desert/desert+13.png" />
        <image file="desert/desert+14.png" />
        <image file="desert/desert+15.png" />
        <image file="desert/desert+16.png" />
        <image file="desert/desert+17.png" />
        <image file="desert/desert+18.png" />
        <image file="desert/desert+19.png" />
        <image file="desert/desert+20.png" />
        <image file="desert/desert+21.png" />
        <image file="desert/desert+W.png" />
        <image file="desert/desert+S.png" />
        <image file="desert/desert+E.png" />
        <image file="desert/desert+N.png" />
        <image file="desert/shadow_desert.png" />

        <image file="desert_forest/desert_forest+style0.png" />
        <image file="desert_forest/desert_forest+style0+E.png" />
        <image file="desert_forest/desert_forest+style0+E+W.png" />
        <image file="desert_forest/desert_forest+style0+W.png" />
        <image file="desert_forest/desert_forest+style0+SE.png" />
        <image file="desert_forest/desert_forest+style0+NE.png" />
        <image file="desert_forest/desert_forest+style0+SW.png" />
        <image file="desert_forest/desert_forest+style0+NW.png" />
        <image file="desert_forest/desert_forest+style1.png" />
        <image file="desert_forest/desert_forest+style1+E.png" />
        <image file="desert_forest/desert_forest+style1+E+W.png" />
        <image file="desert_forest/desert_forest+style1+W.png" />
        <image file="desert_forest/desert_forest+style1+SE.png" />
        <image file="desert_forest/desert_forest+style1+NE.png" />
        <image file="desert_forest/desert_forest+style1+SW.png" />
        <image file="desert_forest/desert_forest+style1+NW.png" />
        
        <image file="wasteland/desert_wasteland+0.png" />
        <image file="wasteland/desert_wasteland+1.png" />
        <image file="wasteland/desert_wasteland+2.png" />
        <image file="wasteland/desert_wasteland+3.png" />
        <image file="wasteland/desert_wasteland+4.png" />
        <image file="wasteland/desert_wasteland+5.png" />
        
        <image file="mountain/desert_rock.png" />
        <image file="mountain/desert_rock+short.png" />

        <image file="desert_pipeline/desert_destroyedweld+E+W.png" />
        <image file="desert_pipeline/desert_destroyedweld+N+S.png" />        
        <image file="desert_pipeline/desert_weld+E+W.png" />
        <image file="desert_pipeline/desert_weld+N+S.png" />
        <image file="desert_pipeline/desert_pipeline.png" />
        <image file="desert_pipeline/desert_pipeline+E.png" />
        <image file="desert_pipeline/desert_pipeline+E+S.png" />
        <image file="desert_pipeline/desert_pipeline+E+S+W.png" />
        <image file="desert_pipeline/desert_pipeline+E+W.png" />
        <image file="desert_pipeline/desert_pipeline+N.png" />
        <image file="desert_pipeline/desert_pipeline+N+E.png" />
        <image file="desert_pipeline/desert_pipeline+N+E+S.png" />
        <image file="desert_pipeline/desert_pipeline+N+E+S+W.png" />
        <image file="desert_pipeline/desert_pipeline+N+E+W.png" />
        <image file="desert_pipeline/desert_pipeline+N+S.png" />
        <image file="desert_pipeline/desert_pipeline+N+S+W.png" />
        <image file="desert_pipeline/desert_pipeline+N+W.png" />
        <image file="desert_pipeline/desert_pipeline+S.png" />
        <image file="desert_pipeline/desert_pipeline+S+W.png" />
        <image file="desert_pipeline/desert_pipeline+W.png" />
        
        <image file="desert_try_river/desert_try_river.png" />
        <image file="desert_try_river/desert_try_river+E.png" />
        <image file="desert_try_river/desert_try_river+E+S.png" />
        <image file="desert_try_river/desert_try_river+E+S+W.png" />
        <image file="desert_try_river/desert_try_river+E+W.png" />
        <image file="desert_try_river/desert_try_river+N.png" />
        <image file="desert_try_river/desert_try_river+N+E.png" />
        <image file="desert_try_river/desert_try_river+N+E+S.png" />
        <image file="desert_try_river/desert_try_river+N+E+S+W.png" />
        <image file="desert_try_river/desert_try_river+N+E+W.png" />
        <image file="desert_try_river/desert_try_river+N+S.png" />
        <image file="desert_try_river/desert_try_river+N+S+W.png" />
        <image file="desert_try_river/desert_try_river+N+W.png" />
        <image file="desert_try_river/desert_try_river+S.png" />
        <image file="desert_try_river/desert_try_river+S+W.png" />
        <image file="desert_try_river/desert_try_river+W.png" />
        
        <image file="desert_path/desert_path+style0.png" />
        <image file="desert_path/desert_path+style0+E.png" />
        <image file="desert_path/desert_path+style0+E+S.png" />
        <image file="desert_path/desert_path+style0+E+S+W.png" />
        <image file="desert_path/desert_path+style0+E+W.png" />
        <image file="desert_path/desert_path+style0+N.png" />
        <image file="desert_path/desert_path+style0+N+E.png" />
        <image file="desert_path/desert_path+style0+N+E+S.png" />
        <image file="desert_path/desert_path+style0+N+E+S+W.png" />
        <image file="desert_path/desert_path+style0+N+E+W.png" />
        <image file="desert_path/desert_path+style0+N+S.png" />
        <image file="desert_path/desert_path+style0+N+S+W.png" />
        <image file="desert_path/desert_path+style0+N+W.png" />
        <image file="desert_path/desert_path+style0+S.png" />
        <image file="desert_path/desert_path+style0+S+W.png" />
        <image file="desert_path/desert_path+style0+W.png" />
        <image file="desert_path/desert_path+style0+shadow.png" />
        <image file="desert_path/desert_path+style0+E+shadow.png" />
        <image file="desert_path/desert_path+style0+E+S+shadow.png" />
        <image file="desert_path/desert_path+style0+E+S+W+shadow.png" />
        <image file="desert_path/desert_path+style0+E+W+shadow.png" />
        <image file="desert_path/desert_path+style0+N+shadow.png" />
        <image file="desert_path/desert_path+style0+N+E+shadow.png" />
        <image file="desert_path/desert_path+style0+N+E+S+shadow.png" />
        <image file="desert_path/desert_path+style0+N+E+S+W+shadow.png" />
        <image file="desert_path/desert_path+style0+N+E+W+shadow.png" />
        <image file="desert_path/desert_path+style0+N+S+shadow.png" />
        <image file="desert_path/desert_path+style0+N+S+W+shadow.png" />
        <image file="desert_path/desert_path+style0+N+W+shadow.png" />
        <image file="desert_path/desert_path+style0+S+shadow.png" />
        <image file="desert_path/desert_path+style0+S+W+shadow.png" />
        <image file="desert_path/desert_path+style0+W+shadow.png" />
        <image file="desert_path/desert_path+style1.png" />
        <image file="desert_path/desert_path+style1+E.png" />
        <image file="desert_path/desert_path+style1+E+S.png" />
        <image file="desert_path/desert_path+style1+E+S+W.png" />
        <image file="desert_path/desert_path+style1+E+W.png" />
        <image file="desert_path/desert_path+style1+N.png" />
        <image file="desert_path/desert_path+style1+N+E.png" />
        <image file="desert_path/desert_path+style1+N+E+S.png" />
        <image file="desert_path/desert_path+style1+N+E+S+W.png" />
        <image file="desert_path/desert_path+style1+N+E+W.png" />
        <image file="desert_path/desert_path+style1+N+S.png" />
        <image file="desert_path/desert_path+style1+N+S+W.png" />
        <image file="desert_path/desert_path+style1+N+W.png" />
        <image file="desert_path/desert_path+style1+S.png" />
        <image file="desert_path/desert_path+style1+S+W.png" />
        <image file="desert_path/desert_path+style1+W.png" />
        
        <image file="ruins/desert_ruin+0.png" />
        <image file="ruins/desert_ruin+1.png" />
        <image file="ruins/desert_ruin+2.png" />
        
        <!-- wasteland -->
        <image file="waste/waste+0.png" />
        <image file="waste/waste+1.png" />
        <image file="waste/waste+2.png" />
        <image file="waste/waste+3.png" />
        <image file="waste/waste+4.png" />
        <image file="waste/waste+5.png" />
        <image file="waste/waste+6.png" />
        <image file="waste/waste+7.png" />
        <image file="waste/waste+8.png" />
        <image file="waste/waste+9.png" />
        <image file="waste/waste+10.png" />
        <image file="waste/waste+11.png" />
        <image file="waste/waste+12.png" />
        <image file="waste/waste+13.png" />
        <image file="waste/waste+14.png" />
        <image file="waste/waste+15.png" />
        <image file="waste/waste+16.png" />
        <image file="waste/waste+17.png" />
        <image file="waste/waste+18.png" />
        <image file="waste/waste+19.png" />
        <image file="waste/waste+20.png" />
        <image file="waste/waste+21.png" />
        <image file="waste/waste+W.png" />
        <image file="waste/waste+S.png" />
        <image file="waste/waste+E.png" />
        <image file="waste/waste+N.png" />
        <image file="waste/shadow_waste.png" />
        
        <image file="waste_forest/waste_forest+style0.png" />
        <image file="waste_forest/waste_forest+style0+E.png" />
        <image file="waste_forest/waste_forest+style0+E+W.png" />
        <image file="waste_forest/waste_forest+style0+W.png" />
        <image file="waste_forest/waste_forest+style0+SE.png" />
        <image file="waste_forest/waste_forest+style0+NE.png" />
        <image file="waste_forest/waste_forest+style0+SW.png" />
        <image file="waste_forest/waste_forest+style0+NW.png" />
        
        <image file="wasteland/waste_wasteland+0.png" />
        <image file="wasteland/waste_wasteland+1.png" />
        <image file="wasteland/waste_wasteland+2.png" />
        <image file="wasteland/waste_wasteland+3.png" />
        <image file="wasteland/waste_wasteland+4.png" />
        <image file="wasteland/waste_wasteland+5.png" />
        
        <image file="mountain/waste_rock.png" />
        <image file="mountain/waste_rock+short.png" />
        
        <image file="ruins/waste_ruin+0.png" />
        <image file="ruins/waste_ruin+1.png" />
        <image file="ruins/waste_ruin+2.png" />

        <image file="waste_path/waste_path+style0.png" />
        <image file="waste_path/waste_path+style0+E.png" />
        <image file="waste_path/waste_path+style0+E+S.png" />
        <image file="waste_path/waste_path+style0+E+S+W.png" />
        <image file="waste_path/waste_path+style0+E+W.png" />
        <image file="waste_path/waste_path+style0+N.png" />
        <image file="waste_path/waste_path+style0+N+E.png" />
        <image file="waste_path/waste_path+style0+N+E+S.png" />
        <image file="waste_path/waste_path+style0+N+E+S+W.png" />
        <image file="waste_path/waste_path+style0+N+E+W.png" />
        <image file="waste_path/waste_path+style0+N+S.png" />
        <image file="waste_path/waste_path+style0+N+S+W.png" />
        <image file="waste_path/waste_path+style0+N+W.png" />
        <image file="waste_path/waste_path+style0+S.png" />
        <image file="waste_path/waste_path+style0+S+W.png" />
        <image file="waste_path/waste_path+style0+W.png" />
        <image file="waste_path/waste_path+style0+shadow.png" />
        <image file="waste_path/waste_path+style0+E+shadow.png" />
        <image file="waste_path/waste_path+style0+E+S+shadow.png" />
        <image file="waste_path/waste_path+style0+E+S+W+shadow.png" />
        <image file="waste_path/waste_path+style0+E+W+shadow.png" />
        <image file="waste_path/waste_path+style0+N+shadow.png" />
        <image file="waste_path/waste_path+style0+N+E+shadow.png" />
        <image file="waste_path/waste_path+style0+N+E+S+shadow.png" />
        <image file="waste_path/waste_path+style0+N+E+S+W+shadow.png" />
        <image file="waste_path/waste_path+style0+N+E+W+shadow.png" />
        <image file="waste_path/waste_path+style0+N+S+shadow.png" />
        <image file="waste_path/waste_path+style0+N+S+W+shadow.png" />
        <image file="waste_path/waste_path+style0+N+W+shadow.png" />
        <image file="waste_path/waste_path+style0+S+shadow.png" />
        <image file="waste_path/waste_path+style0+S+W+shadow.png" />
        <image file="waste_path/waste_path+style0+W+shadow.png" />

        <image file="waste_Pipeline/waste_Pipeline.png" />
        <image file="waste_Pipeline/waste_Pipeline+E.png" />
        <image file="waste_Pipeline/waste_Pipeline+E+S.png" />
        <image file="waste_Pipeline/waste_Pipeline+E+S+W.png" />
        <image file="waste_Pipeline/waste_Pipeline+E+W.png" />
        <image file="waste_Pipeline/waste_Pipeline+N.png" />
        <image file="waste_Pipeline/waste_Pipeline+N+E.png" />
        <image file="waste_Pipeline/waste_Pipeline+N+E+S.png" />
        <image file="waste_Pipeline/waste_Pipeline+N+E+S+W.png" />
        <image file="waste_Pipeline/waste_Pipeline+N+E+W.png" />
        <image file="waste_Pipeline/waste_Pipeline+N+S.png" />
        <image file="waste_Pipeline/waste_Pipeline+N+S+W.png" />
        <image file="waste_Pipeline/waste_Pipeline+N+W.png" />
        <image file="waste_Pipeline/waste_Pipeline+S.png" />
        <image file="waste_Pipeline/waste_Pipeline+S+W.png" />
        <image file="waste_Pipeline/waste_Pipeline+W.png" />
        <image file="waste_Pipeline/waste_weld+E+W.png" />
        <image file="waste_Pipeline/waste_weld+N+S.png" />
        <image file="waste_Pipeline/waste_destroyedweld+E+W.png" />
        <image file="waste_Pipeline/waste_destroyedweld+N+S.png" />

        <!-- teleport tile -->
        <image file="teleporttile/teleporttile.png" />
        <image file="teleporttile/teleporttile+E.png" />
        <image file="teleporttile/teleporttile+E+S.png" />
        <image file="teleporttile/teleporttile+E+S+W.png" />
        <image file="teleporttile/teleporttile+E+W.png" />
        <image file="teleporttile/teleporttile+N.png" />
        <image file="teleporttile/teleporttile+N+E.png" />
        <image file="teleporttile/teleporttile+N+E+S.png" />
        <image file="teleporttile/teleporttile+N+E+S+W.png" />
        <image file="teleporttile/teleporttile+N+E+W.png" />
        <image file="teleporttile/teleporttile+N+S.png" />
        <image file="teleporttile/teleporttile+N+S+W.png" />
        <image file="teleporttile/teleporttile+N+W.png" />
        <image file="teleporttile/teleporttile+S.png" />
        <image file="teleporttile/teleporttile+S+W.png" />
        <image file="teleporttile/teleporttile+W.png" />

        <!-- biomes -->
        <image file="biome_palettes/palette_clear.png" />
        <image file="biome_palettes/palette_waste.png" />
        <image file="biome_palettes/palette_desert.png" />
        <image file="biome_palettes/palette_snow.png" />

        <image file="biome_palettes/palette_clear+aw1.png" />
        <image file="biome_palettes/palette_snow+aw1.png" />

        <image file="biome_palettes/palette_clear+aw2.png" />
        <image file="biome_palettes/palette_rain+aw2.png" />
        <image file="biome_palettes/palette_snow+aw2.png" />

        <image file="biome_palettes/palette_clear+awds.png" />
        <image file="biome_palettes/palette_desert+awds.png" />
        <image file="biome_palettes/palette_snow+awds.png" />
        <image file="biome_palettes/palette_waste+awds.png" />

        <image file="biome_palettes/palette_clear+dor.png" />
        <image file="biome_palettes/palette_desert+dor.png" />
        <image file="biome_palettes/palette_snow+dor.png" />
        <image file="biome_palettes/palette_waste+dor.png" />

        <image file="biome_palettes/palette_clear+wg.png" />
        <image file="biome_palettes/palette_desert+wg.png" />
        <image file="biome_palettes/palette_snow+wg.png" />
        <image file="biome_palettes/palette_waste+wg.png" />

        <image file="biome_palettes/palette_clear+sfw.png" />
        <image file="biome_palettes/palette_desert+sfw.png" />
        <image file="biome_palettes/palette_snow+sfw.png" />
        <image file="biome_palettes/palette_waste+sfw.png" />
    </atlas>
</resources>
